doctor_wheel/__init__.py
doctor_wheel/run.py
doctor_wheel-1.2.dist-info/LICENSE
doctor_wheel-1.2.dist-info/METADATA
doctor_wheel-1.2.dist-info/WHEEL
doctor_wheel-1.2.dist-info/entry_points.txt
doctor_wheel-1.2.dist-info/top_level.txt
doctor_wheel-1.2.dist-info/RECORD
