Metadata-Version: 2.1
Name: doctor-wheel
Version: 1.2
Summary: A utility to strip and reduce the size of your wheels
Home-page: https://github.com/smok-serwis/doctor-wheel
Author: Piotr Maślanka
Author-email: pmaslanka@smok.co
License: UNKNOWN
Project-URL: Code, https://github.com/smok-serwis/doctor-wheel
Project-URL: Issue tracker, https://github.com/smok-serwis/doctor-wheel/issues
Keywords: wheel,strip,size,reduction
Platform: UNKNOWN
Classifier: Programming Language :: Python
Classifier: Programming Language :: Python :: 2.7
Classifier: Programming Language :: Python :: 3.3
Classifier: Programming Language :: Python :: 3.4
Classifier: Programming Language :: Python :: 3.5
Classifier: Programming Language :: Python :: 3.6
Classifier: Programming Language :: Python :: 3.7
Classifier: Programming Language :: Python :: 3.8
Classifier: Programming Language :: Python :: 3.9
Classifier: Programming Language :: Python :: Implementation :: CPython
Classifier: Operating System :: POSIX
Classifier: Operating System :: OS Independent
Classifier: Development Status :: 5 - Production/Stable
Classifier: License :: OSI Approved :: MIT License
Classifier: Topic :: System :: Software Distribution
